postcard_creator-0.0.8.dist-info/RECORD
postcard_creator-0.0.8.dist-info/metadata.json
postcard_creator-0.0.8.dist-info/WHEEL
postcard_creator-0.0.8.dist-info/DESCRIPTION.rst
postcard_creator-0.0.8.dist-info/top_level.txt
postcard_creator-0.0.8.dist-info/METADATA
postcard_creator/__init__.py
postcard_creator/page_1.svg
postcard_creator/page_2.svg
postcard_creator/postcard_creator.py
