Metadata-Version: 2.0
Name: postcard-creator
Version: 0.0.8
Summary: A python wrapper around the Rest API of the Swiss Postcard creator
Home-page: http://github.com/abertschi/postcard_creator_wrapper
Author: Andrin Bertschi
Author-email: UNKNOWN
License: Apache Software License
Keywords: postcard creator swiss
Platform: any
Classifier: Intended Audience :: Developers
Classifier: Programming Language :: Python :: 3.3
Classifier: Programming Language :: Python :: 3.4
Classifier: Programming Language :: Python :: 3.5
Classifier: Programming Language :: Python :: 3.6
Requires-Dist: beautifulsoup4
Requires-Dist: Pillow
Requires-Dist: requests-toolbelt
Requires-Dist: cookies
Requires-Dist: idna
Requires-Dist: requests
Requires-Dist: urllib3
Requires-Dist: python-resize-image
